thonnycontrib/__init__.py
thonnycontrib/thonny-LoggingPlugin.py
thonnycontrib/thonny_LoggingPlugin/__init__.py
thonnycontrib/thonny_LoggingPlugin/mainApp.py
thonnycontrib/thonny_LoggingPlugin/communication/__init__.py
thonnycontrib/thonny_LoggingPlugin/communication/sendingClient.py
thonnycontrib/thonny_LoggingPlugin/configuration/__init__.py
thonnycontrib/thonny_LoggingPlugin/configuration/configuration.py
thonnycontrib/thonny_LoggingPlugin/configuration/globals.py
thonnycontrib/thonny_LoggingPlugin/formats/__init__.py
thonnycontrib/thonny_LoggingPlugin/formats/xAPI_creation.py
thonnycontrib/thonny_LoggingPlugin/processing/__init__.py
thonnycontrib/thonny_LoggingPlugin/processing/formatData.py
thonny_LoggingPlugin-0.1.11.dist-info/LICENSE
thonny_LoggingPlugin-0.1.11.dist-info/METADATA
thonny_LoggingPlugin-0.1.11.dist-info/WHEEL
thonny_LoggingPlugin-0.1.11.dist-info/top_level.txt
thonny_LoggingPlugin-0.1.11.dist-info/RECORD
