Metadata-Version: 2.1
Name: thonny-LoggingPlugin
Version: 0.1.11
Summary: A plugin that logs and send all the user's actions to an LRS
Home-page: https://gitlab.univ-lille.fr/corentin.duvivier.etu/thonny-plugin-journalisation
Author: Corentin
Author-email: corentin.duvivier.etu@univ-lille.fr
Platform: Windows
Platform: macOS
Platform: Linux
Classifier: Programming Language :: Python :: 3
Classifier: License :: OSI Approved :: MIT License
Classifier: Operating System :: OS Independent
Requires-Python: >=3.6
License-File: LICENSE
Requires-Dist: thonny (>=3.3.13)
